NiukeShangyeChanpinXiaozhaoQiuzhiGonglve20212022/README.md
NiukeShangyeChanpinXiaozhaoQiuzhiGonglve20212022/__init__.py
NiukeShangyeChanpinXiaozhaoQiuzhiGonglve20212022/__main__.py
NiukeShangyeChanpinXiaozhaoQiuzhiGonglve20212022/file.epub
NiukeShangyeChanpinXiaozhaoQiuzhiGonglve20212022/index.html
NiukeShangyeChanpinXiaozhaoQiuzhiGonglve20212022/css/__init__.py
NiukeShangyeChanpinXiaozhaoQiuzhiGonglve20212022/css/annotations.css
NiukeShangyeChanpinXiaozhaoQiuzhiGonglve20212022/css/main.css
NiukeShangyeChanpinXiaozhaoQiuzhiGonglve20212022/css/normalize.css
NiukeShangyeChanpinXiaozhaoQiuzhiGonglve20212022/css/popup.css
NiukeShangyeChanpinXiaozhaoQiuzhiGonglve20212022/font/__init__.py
NiukeShangyeChanpinXiaozhaoQiuzhiGonglve20212022/font/fontello.eot
NiukeShangyeChanpinXiaozhaoQiuzhiGonglve20212022/font/fontello.svg
NiukeShangyeChanpinXiaozhaoQiuzhiGonglve20212022/font/fontello.ttf
NiukeShangyeChanpinXiaozhaoQiuzhiGonglve20212022/font/fontello.woff
NiukeShangyeChanpinXiaozhaoQiuzhiGonglve20212022/img/__init__.py
NiukeShangyeChanpinXiaozhaoQiuzhiGonglve20212022/img/annotator-glyph-sprite.png
NiukeShangyeChanpinXiaozhaoQiuzhiGonglve20212022/img/annotator-icon-sprite.png
NiukeShangyeChanpinXiaozhaoQiuzhiGonglve20212022/img/apple-touch-icon.png
NiukeShangyeChanpinXiaozhaoQiuzhiGonglve20212022/img/cancelfullscreen.png
NiukeShangyeChanpinXiaozhaoQiuzhiGonglve20212022/img/close.png
NiukeShangyeChanpinXiaozhaoQiuzhiGonglve20212022/img/fullscreen.png
NiukeShangyeChanpinXiaozhaoQiuzhiGonglve20212022/img/loader.gif
NiukeShangyeChanpinXiaozhaoQiuzhiGonglve20212022/img/menu-icon.png
NiukeShangyeChanpinXiaozhaoQiuzhiGonglve20212022/img/save.png
NiukeShangyeChanpinXiaozhaoQiuzhiGonglve20212022/img/saved.png
NiukeShangyeChanpinXiaozhaoQiuzhiGonglve20212022/img/settings-s.png
NiukeShangyeChanpinXiaozhaoQiuzhiGonglve20212022/img/settings.png
NiukeShangyeChanpinXiaozhaoQiuzhiGonglve20212022/img/star.png
NiukeShangyeChanpinXiaozhaoQiuzhiGonglve20212022/js/__init__.py
niuke_shangye_chanpin_xiaozhao_qiuzhi_gonglve_2021_2022-2024.3.6.0.dist-info/METADATA
niuke_shangye_chanpin_xiaozhao_qiuzhi_gonglve_2021_2022-2024.3.6.0.dist-info/WHEEL
niuke_shangye_chanpin_xiaozhao_qiuzhi_gonglve_2021_2022-2024.3.6.0.dist-info/entry_points.txt
niuke_shangye_chanpin_xiaozhao_qiuzhi_gonglve_2021_2022-2024.3.6.0.dist-info/top_level.txt
niuke_shangye_chanpin_xiaozhao_qiuzhi_gonglve_2021_2022-2024.3.6.0.dist-info/RECORD
